venvs/__init__.py
venvs/_cli.py
venvs/_config.py
venvs/common.py
venvs/converge.py
venvs/create.py
venvs/find.py
venvs/remove.py
venvs/temporary.py
venvs/tests/__init__.py
venvs/tests/test_common.py
venvs/tests/test_config.py
venvs/tests/test_converge.py
venvs/tests/test_create.py
venvs/tests/test_find.py
venvs/tests/test_remove.py
venvs/tests/test_temporary.py
venvs/tests/utils.py
venvs-2024.8.2.dist-info/METADATA
venvs-2024.8.2.dist-info/WHEEL
venvs-2024.8.2.dist-info/entry_points.txt
venvs-2024.8.2.dist-info/licenses/COPYING
venvs-2024.8.2.dist-info/RECORD
