Metadata-Version: 2.3
Name: venvs
Version: 2024.8.2
Summary: A simpler tool for creating venvs in a central location
Project-URL: Documentation, https://venvs.readthedocs.io/
Project-URL: Homepage, https://github.com/Julian/venvs
Project-URL: Issues, https://github.com/Julian/venvs/issues/
Project-URL: Funding, https://github.com/sponsors/Julian
Project-URL: Source, https://github.com/python-jsonschema/referencing
Author-email: Julian Berman <Julian+venvs@GrayVines.com>
License-File: COPYING
Keywords: mkvirtualenv,pipx,venv,virtualenv,virtualenvwrapper
Classifier: Development Status :: 4 - Beta
Classifier: Intended Audience :: Developers
Classifier: License :: OSI Approved :: MIT License
Classifier: Operating System :: OS Independent
Classifier: Programming Language :: Python
Classifier: Programming Language :: Python :: 3.10
Classifier: Programming Language :: Python :: 3.11
Classifier: Programming Language :: Python :: 3.12
Classifier: Programming Language :: Python :: Implementation :: CPython
Classifier: Programming Language :: Python :: Implementation :: PyPy
Requires-Python: >=3.10
Requires-Dist: attrs>=23.1.0
Requires-Dist: click
Requires-Dist: filesystems>=2024.8.1
Requires-Dist: packaging
Requires-Dist: platformdirs
Requires-Dist: pyrsistent
Requires-Dist: toml>=0.10.0
Requires-Dist: tomlkit
Requires-Dist: tqdm
Requires-Dist: uv>=0.1.13
